Workbook

Sheet Hoja6
B1: Preguntas | C1: Respuestas
A2: Tecsa | B2: =COUNTIFS('Tabla General'!$F:$F,"<>",'Tabla General'!$C:$C,Hoja6!A2) -> 140 | C2: =COUNTIFS('Tabla General'!$H:$H,"<>",'Tabla General'!$C:$C,Hoja6!A2) -> 140
A3: Propamat | B3: =COUNTIFS('Tabla General'!$F:$F,"<>",'Tabla General'!$C:$C,Hoja6!A3) -> 50 | C3: =COUNTIFS('Tabla General'!$H:$H,"<>",'Tabla General'!$C:$C,Hoja6!A3) -> 50
A4: Fleischmann S. A. | B4: =COUNTIFS('Tabla General'!$F:$F,"<>",'Tabla General'!$C:$C,Hoja6!A4) -> 117 | C4: =COUNTIFS('Tabla General'!$H:$H,"<>",'Tabla General'!$C:$C,Hoja6!A4) -> 117
A5: Global Data | B5: =COUNTIFS('Tabla General'!$F:$F,"<>",'Tabla General'!$C:$C,Hoja6!A5) -> 142 | C5: =COUNTIFS('Tabla General'!$H:$H,"<>",'Tabla General'!$C:$C,Hoja6!A5) -> 142
A6: CS Energy | B6: =COUNTIFS('Tabla General'!$F:$F,"<>",'Tabla General'!$C:$C,Hoja6!A6) -> 29 | C6: =COUNTIFS('Tabla General'!$H:$H,"<>",'Tabla General'!$C:$C,Hoja6!A6) -> 29
B7: =SUM(B2:B6) -> 478 | C7: =SUM(C2:C6) -> 478
A9: GENERAL/ADM | B9: =COUNTIFS('Tabla General'!F:F,"<>",'Tabla General'!E:E,Hoja6!A9) -> 58 | C9: =COUNTIFS('Tabla General'!J:J,"Respondido",'Tabla General'!E:E,Hoja6!A9) -> 58
A10: OOCC | B10: =COUNTIFS('Tabla General'!F:F,"<>",'Tabla General'!E:E,Hoja6!A10) -> 64 | C10: =COUNTIFS('Tabla General'!J:J,"Respondido",'Tabla General'!E:E,Hoja6!A10) -> 64
A11: BMS | B11: =COUNTIFS('Tabla General'!F:F,"<>",'Tabla General'!E:E,Hoja6!A11) -> 26 | C11: =COUNTIFS('Tabla General'!J:J,"Respondido",'Tabla General'!E:E,Hoja6!A11) -> 26
A12: SEGURIDAD | B12: =COUNTIFS('Tabla General'!F:F,"<>",'Tabla General'!E:E,Hoja6!A12) -> 19 | C12: =COUNTIFS('Tabla General'!J:J,"Respondido",'Tabla General'!E:E,Hoja6!A12) -> 19
A13: TELECOM | B13: =COUNTIFS('Tabla General'!F:F,"<>",'Tabla General'!E:E,Hoja6!A13) -> 111 | C13: =COUNTIFS('Tabla General'!J:J,"Respondido",'Tabla General'!E:E,Hoja6!A13) -> 111
A14: ELECTRICO | B14: =COUNTIFS('Tabla General'!F:F,"<>",'Tabla General'!E:E,Hoja6!A14) -> 96 | C14: =COUNTIFS('Tabla General'!J:J,"Respondido",'Tabla General'!E:E,Hoja6!A14) -> 96
A15: HVAC | B15: =COUNTIFS('Tabla General'!F:F,"<>",'Tabla General'!E:E,Hoja6!A15) -> 60 | C15: =COUNTIFS('Tabla General'!J:J,"Respondido",'Tabla General'!E:E,Hoja6!A15) -> 60
A16: PCI | B16: =COUNTIFS('Tabla General'!F:F,"<>",'Tabla General'!E:E,Hoja6!A16) -> 6 | C16: =COUNTIFS('Tabla General'!J:J,"Respondido",'Tabla General'!E:E,Hoja6!A16) -> 6
A17: IIFF | B17: =COUNTIFS('Tabla General'!F:F,"<>",'Tabla General'!E:E,Hoja6!A17) -> 19 | C17: =COUNTIFS('Tabla General'!J:J,"Respondido",'Tabla General'!E:E,Hoja6!A17) -> 19
A18: EHS | B18: =COUNTIFS('Tabla General'!F:F,"<>",'Tabla General'!E:E,Hoja6!A18) -> 4 | C18: =COUNTIFS('Tabla General'!J:J,"Respondido",'Tabla General'!E:E,Hoja6!A18) -> 4
A19: COMISIONAMIENTO | B19: =COUNTIFS('Tabla General'!F:F,"<>",'Tabla General'!E:E,Hoja6!A19) -> 5 | C19: =COUNTIFS('Tabla General'!J:J,"Respondido",'Tabla General'!E:E,Hoja6!A19) -> 5
A20: DETECCION | B20: =COUNTIFS('Tabla General'!F:F,"<>",'Tabla General'!E:E,Hoja6!A20) -> 10 | C20: =COUNTIFS('Tabla General'!J:J,"Respondido",'Tabla General'!E:E,Hoja6!A20) -> 10
B21: =SUM(B9:B20) -> 478 | C21: =SUM(C9:C20) -> 478

Sheet Tabla General
A1: Sitio: Odata ST01 EX05
A2: Proyecto: RFP ODATA -DC ST01 EX05
A4: n° | B4: n° interno | C4: GC | D4: Tipo de Consulta | E4: Especialidad | F4: Pregunta | G4: Documento relacionado | H4: Respuesta | I4: Observación | J4: Respondido | K4: Columna1
A5: 460 | B5: 43 | C5: Fleischmann S. A. | E5: SEGURIDAD | F5: indicar que software o plataforma es la existente para sistema de CCTV y Control de Acceso | H5: Avigilion. | J5: =IF(Tabla1[[#This Row],[Respuesta]]="","Sin respuesta","Respondido") -> Respondido | K5: Validar con Oscar Lopez
A6: 357 | B6: 105 | C6: Tecsa | E6: BMS | F6: BMS: Confirmar que la licencia requerida para la plataforma Ignition es la versión Pro | H6: Ignition, considerar licencia para Gateway principal y otra para Gateway de respaldo. | J6: =IF(Tabla1[[#This Row],[Respuesta]]="","Sin respuesta","Respondido") -> Respondido | K6: Preguntar a Oscar Lopez de Odata
A7: 274 | B7: 22 | C7: Tecsa | E7: BMS | F7: SEGURIDAD ELECTRONICA: Favor mencionar modelo, marca, y versión del BMS actual. | H7: Securtity expert. | J7: =IF(Tabla1[[#This Row],[Respuesta]]="","Sin respuesta","Respondido") -> Respondido | K7: Preguntar a Oscar Lopez de Odata
A8: 478 | B8: 61 | C8: Fleischmann S. A. | E8: HVAC | F8: Por favor indicar caída de presión para poder cotizar equipos fan-coils. | G8: =#VALUE! -> #VALUE! | H8: No considerar fancoils. | J8: =IF(Tabla1[[#This Row],[Respuesta]]="","Sin respuesta","Respondido") -> Respondido
A9: 477 | B9: 60 | C9: Fleischmann S. A. | E9: HVAC | F9: Por favor aclarar porque la ficha de equipos fancoils esta dentro de una carpeta que dice anulados. | G9: ODA-0004-CLI-HD-009 | H9: No considerar fancoils. | J9: =IF(Tabla1[[#This Row],[Respuesta]]="","Sin respuesta","Respondido") -> Respondido
A10: 476 | B10: 59 | C10: Fleischmann S. A. | E10: HVAC | F10: Confirmar que los equipos CRAC son suministrados por Odata, ya que en pagina 23 de EE.TT. No se menciona. Sin embargo se entrega documento ODA-0004-CLI-RFQ-005 que confunde porque es el mismo documento para equipos: Chillers, deltacube, crah que son suministrados por Odata. Por favor aclarar | G10: RFP INSTALCIONES EX05_REV2, página 23 | H10: Ver respuesta 83. | J10: =IF(Tabla1[[#This Row],[Respuesta]]="","Sin respuesta","Respondido") -> Respondido
A11: 475 | B11: 58 | C11: Fleischmann S. A. | E11: HVAC | F11: Por favor indicar cuanto peso por m2 resiste la viga para poder calcular el soporte de cañerías y el soporte considerado puede perforar la viga? | G11: =#VALUE! -> #VALUE! | H11: Ver Respuesta 448. | J11: =IF(Tabla1[[#This Row],[Respuesta]]="","Sin respuesta","Respondido") -> Respondido
A12: 474 | B12: 57 | C12: Fleischmann S. A. | E12: HVAC | F12: Confirmar norma ASME B31.3 para soldadura por lo tanto no se requiere tintas penetrantes ni ensayos radiográficos | G12: ODA-0004-CLI-ET-009 | H12: Ver respuesta 473. | J12: =IF(Tabla1[[#This Row],[Respuesta]]="","Sin respuesta","Respondido") -> Respondido
A13: 473 | B13: 56 | C13: Fleischmann S. A. | E13: HVAC | F13: Por favor confirmar que podemos trabajar bajo norma ASME B31.3 y no bajo norma AWSD 1.1 solicitada en documento. La norma solicitada se utiliza en el diseños de estructuras y no aplica para la especialidad de climatización que trabaja a baja presiones. | G13: ODA-0004-CLI-ET-009 | H13: Confirmamos que, para el alcance de climatización, corresponde la aplicación de la norma ASME B31.3 (Process Piping) . No obstante, en relación con los soportes de tuberías y equipos, estos constituyen elementos de carácter estructural secundario, por lo que las soldaduras asociadas se encuentran reguladas por la norma AWS D1.1 – Structural Welding Code – Steel. En ambos casos el Proponente deberá presentar los dossier de Calidad de los suministros con sus respectivos ensayos, siendo obligatoria en todo caso la inspección certificada de las soldaduras. | J13: =IF(Tabla1[[#This Row],[Respuesta]]="","Sin respuesta","Respondido") -> Respondido
A14: 472 | B14: 55 | C14: Fleischmann S. A. | E14: HVAC | F14: Indicar si la cantidad de equipos CRAC-FCU-BMS corresponden a 2 o 3 unidades (Planos figuran 2, fichas figuran 3 unidades) | G14: ODA-0004-CLI-PL-003 | H14: Existen de ambas configuraciones. | J14: =IF(Tabla1[[#This Row],[Respuesta]]="","Sin respuesta","Respondido") -> Respondido
A15: 471 | B15: 54 | C15: Fleischmann S. A. | E15: TELECOM | F15: Se solicita confirmar la necesidad de demoler el tramo de banco de ductos señalado en el plano ODA-0004-TEL-PL-0004, tomando en cuenta que los pavimentos de hormigón en dicho sector están terminados. | G15: ODA-0004-TEL-PL-0004 | H15: No, las partidas de ese plano ya están ejecutadas | J15: =IF(Tabla1[[#This Row],[Respuesta]]="","Sin respuesta","Respondido") -> Respondido
A16: 470 | B16: 53 | C16: Fleischmann S. A. | E16: OOCC | F16: Se solicita entregar el plano de estructura de la parrilla nivel +497,4, indicado en listado de planos (ODA-0004-EST-PL-020). Se requiere para evaluar apropiadamente los soportes de las instalaciones y cielos falsos que deben colgarse de la misma | G16: ODA-0004-ARQ-PL-097 | H16: Se adjunta. | J16: =IF(Tabla1[[#This Row],[Respuesta]]="","Sin respuesta","Respondido") -> Respondido
A17: 469 | B17: 52 | C17: Fleischmann S. A. | E17: OOCC | F17: De acuerdo a lo señalado en el punto 5.10.2 de las EE.TT. Los revestimientos en ambas caras deben recubrir todos los elementos estructurales dejando una superficie lisa desde el NPT hasta el cielo o remate de encuentro superior. Se solicita confirmar que no se requieren pinturas sobre el nivel de cielo falso. | G17: ODA-0004-ARQ-ET-001 | H17: Si, se confirma solo para los recintos que tienen cielo falsos. | J17: =IF(Tabla1[[#This Row],[Respuesta]]="","Sin respuesta","Respondido") -> Respondido
A18: 468 | B18: 51 | C18: Fleischmann S. A. | E18: OOCC | F18: Se solicita confirmar que los refuerzos en tabiques y ventanas se encuentran ejecutados, y que sólo se requiere verificar las medidas antes de mandar a fabricar. En caso contrario se requiere que nos entreguen los planos de estructuras correspondientes | G18: ODA-0004-ARQ-ET-001 | H18: Ver respuesta 51. | J18: =IF(Tabla1[[#This Row],[Respuesta]]="","Sin respuesta","Respondido") -> Respondido
A19: 467 | B19: 50 | C19: Fleischmann S. A. | E19: OOCC | F19: Se solicita confirmar que los refuerzos en tabiques y ventanas se encuentran ejecutados, y que sólo se requiere verificar las medidas antes de mandar a fabricar. En caso contrario se requiere que nos entreguen los planos de estructuras correspondientes | G19: ODA-0004-ARQ-ET-001 | H19: Ver respuesta 51. | J19: =IF(Tabla1[[#This Row],[Respuesta]]="","Sin respuesta","Respondido") -> Respondido
A20: 466 | B20: 49 | C20: Fleischmann S. A. | E20: OOCC | F20: Se solicita confirmar que todas las estructuras que requieren protección al fuego mediante pintura intumescente ya están pintadas, incluyendo las escaleras de escape. De no ser así, se requiere la entrega de los planos de cálculo para hacer estudio de masividades y poder estimar los espesores requeridos de acuerdo a lo señalado en el punto 6.7.3 de las EE.TT., o que se entreguen los esquemas de pintura a utilizar. | G20: ODA-0004-ARQ-ET-001 | H20: No es alcance de este RFP la estructura principal y pintura intumescente. | J20: =IF(Tabla1[[#This Row],[Respuesta]]="","Sin respuesta","Respondido") -> Respondido
A21: 465 | B21: 48 | C21: Fleischmann S. A. | E21: TELECOM | F21: Confirmar que el 100% de racks y PDU serán parte del suministro ODATA. ( Rack Principal y Rack de acceso) | H21: Odata proveerá los racks del proyecto, estos serán entregados sobre camión en obra. El proponente deberá realizar su desplazamiento horizontal y vertical hasta su punto de instalación, realizando los respectivos anclajes del mismo e instalando todos los dispositivos asociados al mismo. | J21: =IF(Tabla1[[#This Row],[Respuesta]]="","Sin respuesta","Respondido") -> Respondido
A22: 464 | B22: 47 | C22: Fleischmann S. A. | E22: TELECOM | F22: Confirmar que los equipos Access Point serán parte del suministro ODATA | H22: Si, se confirma. | J22: =IF(Tabla1[[#This Row],[Respuesta]]="","Sin respuesta","Respondido") -> Respondido
A23: 463 | B23: 46 | C23: Fleischmann S. A. | E23: TELECOM | F23: Se deberá considerar en esta etapa canalizaciones Fiber Runner. | H23: No forma parte del alcance de este RFP | J23: =IF(Tabla1[[#This Row],[Respuesta]]="","Sin respuesta","Respondido") -> Respondido
A24: 462 | B24: 45 | C24: Fleischmann S. A. | E24: DETECCION | F24: Se deberá considerar Estación de Monitoreo (Onyxworks) para sistema de detección de incendio o este es existente en etapa anterior | H24: Si, se debe considerar una Estacion de Monitoreo. | J24: =IF(Tabla1[[#This Row],[Respuesta]]="","Sin respuesta","Respondido") -> Respondido
A25: 461 | B25: 44 | C25: Fleischmann S. A. | E25: SEGURIDAD | F25: Para la ejecución de sistemas de Seguridad Electrónica se deberán considerar subcontrato aprobados por Odata, o podremos utilizar mano de obra calificada y certificada propia del proponente. | H25: Pueden utilizar mano de obra calificada y certificada por el Proponente | J25: =IF(Tabla1[[#This Row],[Respuesta]]="","Sin respuesta","Respondido") -> Respondido
A26: 459 | B26: 42 | C26: Fleischmann S. A. | E26: SEGURIDAD | F26: Favor confirmar marca y modelos de Cámaras de sistema Video Vigilancia | H26: Cámaras marca Pelco | J26: =IF(Tabla1[[#This Row],[Respuesta]]="","Sin respuesta","Respondido") -> Respondido
A27: 458 | B27: 41 | C27: Fleischmann S. A. | E27: IIFF | F27: Según lo indicado en el RFP INSTALCIONES EX05_REV2 se solicita indica en ANEXO XIII no indica el uso del edificio que se muestra en planta entre zona 2 Y ZONA 6. Esta zona estará disponible para su uso? | G27: 5.1.1 ORGANIZACIÓN DE LA INSTALACIÓN DE FAENA, Anexo XIII_Esquema Instalación de Faenas | H27: Ver Respuesta 457 | J27: =IF(Tabla1[[#This Row],[Respuesta]]="","Sin respuesta","Respondido") -> Respondido
A28: 457 | B28: 40 | C28: Fleischmann S. A. | E28: IIFF | F28: Según lo indicado en el RFP INSTALCIONES EX05_REV2 se solicita indica en ANEXO XIII posibles ubicaciones para futuros contenedores. Se solicita indicar si las zonas junto a los estacionamientos, donde se ven materiales al suelo , estará despejada y disponible para uso. | G28: 5.1.1 ORGANIZACIÓN DE LA INSTALACIÓN DE FAENA, Anexo XIII_Esquema Instalación de Faenas | H28: Si, se confirma lo indicado. No obstante, el PROPONENTE deberá presentar un Plan de Movilización e Instalaciones de Faena para su revisión y aprobación por parte de ODATA, como requisito previo al inicio de los trabajos. | J28: =IF(Tabla1[[#This Row],[Respuesta]]="","Sin respuesta","Respondido") -> Respondido
A29: 456 | B29: 39 | C29: Fleischmann S. A. | E29: IIFF | F29: Según lo indicado en el RFP INSTALCIONES EX05_REV2 se solicita indica si la bodega Odata N° 3 del ANEXO XIII estará disponible para uso del proponente. | G29: 5.1.1 ORGANIZACIÓN DE LA INSTALACIÓN DE FAENA, Anexo XIII_Esquema Instalación de Faenas | H29: No, es uso exclusivo de Odata | J29: =IF(Tabla1[[#This Row],[Respuesta]]="","Sin respuesta","Respondido") -> Respondido
A30: 455 | B30: 38 | C30: Fleischmann S. A. | E30: IIFF | F30: Según lo indicado en el RFP INSTALCIONES EX05_REV2 se solicita indica capacidad para comedor, no indicado en el ANEXO XIII | G30: 5.1.1 ORGANIZACIÓN DE LA INSTALACIÓN DE FAENA, Anexo XIII_Esquema Instalación de Faenas | H30: Son 6 módulos con capacidad para 30 personas cada uno. | J30: =IF(Tabla1[[#This Row],[Respuesta]]="","Sin respuesta","Respondido") -> Respondido
A31: 454 | B31: 37 | C31: Fleischmann S. A. | E31: IIFF | F31: Según lo indicado en el RFP INSTALCIONES EX05_REV2 Se solicita indica la capacidad eléctrica del instalación de faena actual y disponibilidad de potencia para conexión de futuros contenedores. | G31: 5.1.1 ORGANIZACIÓN DE LA INSTALACIÓN DE FAENA | H31: Empalme de 300 kVA | J31: =IF(Tabla1[[#This Row],[Respuesta]]="","Sin respuesta","Respondido") -> Respondido
A32: 453 | B32: 36 | C32: Fleischmann S. A. | E32: GENERAL/ADM | F32: En base a la respuesta N°55 Se solicita indicar el alcance del permiso de edificación actual si tienen incluidas las obras de este contrato y solo se debe modificar el constructor, favor compartir el permiso actual de construcción. | H32: Existe permiso de edificación para la ejecución de las obras de este contrato. | J32: =IF(Tabla1[[#This Row],[Respuesta]]="","Sin respuesta","Respondido") -> Respondido
A33: 452 | B33: 35 | C33: Fleischmann S. A. | E33: GENERAL/ADM | F33: Según lo indicado en el RFP INSTALCIONES EX05_REV2 se solicita indicar si los TAG de los equipos suministrados por el cliente, son del alcance del proveedor. | G33: 4.6 TAG – Identificación de los equipos | H33: Son alcance del proveedor | J33: =IF(Tabla1[[#This Row],[Respuesta]]="","Sin respuesta","Respondido") -> Respondido
A34: 451 | B34: 34 | C34: Fleischmann S. A. | E34: GENERAL/ADM | F34: Según lo indicado en el RFP INSTALCIONES EX05_REV2 se solicita indicar si los TAG son solo en español. | G34: 4.6 TAG – Identificación de los equipos | H34: Si, solo en español | J34: =IF(Tabla1[[#This Row],[Respuesta]]="","Sin respuesta","Respondido") -> Respondido
A35: 450 | B35: 33 | C35: Fleischmann S. A. | E35: GENERAL/ADM | F35: Según lo indicado en el RFP INSTALCIONES EX05_REV2, De acuerdo a la respuesta N°63,64,65,66,68 .Se solicita aclarar que partidas requieren Ensayos de hormigón y acero estructural, Ensayos de compactación de suelos, Áreas sometidas a procesos de impermeabilización, en vista que las respuesta anteriores indican que esto no es parte del alcance y que está ejecutado. | G35: 4.5 Control de calidad – Materiales y servicios | H35: De acuerdo a lo especificado y normativa nacional vigente para las partidas que se ejecutaran. | J35: =IF(Tabla1[[#This Row],[Respuesta]]="","Sin respuesta","Respondido") -> Respondido
A36: 449 | B36: 32 | C36: Fleischmann S. A. | E36: GENERAL/ADM | F36: Se solicita aclaración para dar cumplimiento al pto 4.3.8 RFP INSTALCIONES EX05_REV2 , el hito indicado en el Anexo III "Entrega final de ingeniería de suportaciones" es de responsabilidad del proponente? , en caso de ser afirmativo, se requiere fecha de entrega de PLANOS y MODELO BIM IFC coordinado con la parrilla existente (alturas y ubicación) ya que hay instalaciones que chocan con vigas estructurales en el modelo entregado. | G36: ANEXO III_Programa de Construcción ST01 Fase 5-E2_revA, RFP INSTALCIONES EX05_REV2 | H36: Es responsabilidad del Proponente, ver respuestas 23, 140, 236 y 241 . Ver numerales 4.3.8, 5.4 y 5.5 del RFP | J36: =IF(Tabla1[[#This Row],[Respuesta]]="","Sin respuesta","Respondido") -> Respondido
A37: 448 | B37: 31 | C37: Fleischmann S. A. | E37: OOCC | F37: Se solicita enviar memorias de cálculo de la parrilla metálica destinada a la suspensión de cielos e instalaciones, incluyendo la capacidad portante y límites de carga admisibles del sistema., que contenga Esquemas y planos de la parrilla metálica. criterios de diseño y normas de referencia utilizadas, cálculos de capacidad de carga y factores de seguridad considerados, recomendaciones para la configuración de la Soportación en función de los pesos previstos. | G37: 4.3.8 Ingeniería y Suministro de Sistemas de Soportación de especialidades. | H37: Se adjunta. | J37: =IF(Tabla1[[#This Row],[Respuesta]]="","Sin respuesta","Respondido") -> Respondido
A38: 447 | B38: 30 | C38: Fleischmann S. A. | E38: GENERAL/ADM | F38: Indicar si la Carta Gantt recibida como antecedente tiene días corridos o hábiles, además el calendario no contienen feriados. | H38: Debe ser utilizada para entender los plazos generales, la programación de la obra y la configuración de días trabajados feriados etc., es de exclusiva responsabilidad del proponente. | J38: =IF(Tabla1[[#This Row],[Respuesta]]="","Sin respuesta","Respondido") -> Respondido
A39: 446 | B39: 29 | C39: Fleischmann S. A. | E39: BMS | F39: La canalización de Fibra Óptica (Fiber Runner) se deberá considerar en esta etapa junto con las bajadas a cada Rack? | H39: No | J39: =IF(Tabla1[[#This Row],[Respuesta]]="","Sin respuesta","Respondido") -> Respondido
A40: 445 | B40: 28 | C40: Fleischmann S. A. | E40: BMS | F40: Estación de Monitoreo (Onyxworks) Se deberá considerar para esta etapa o es existente en etapas anteriores? | H40: Se debe considerar | J40: =IF(Tabla1[[#This Row],[Respuesta]]="","Sin respuesta","Respondido") -> Respondido
A41: 444 | B41: 27 | C41: Fleischmann S. A. | E41: ELECTRICO | F41: Se solicita mode y marca de los sensores de movimiento, o equivalente técnico. | H41: El proveedor adjudicado deberá presentar la propuesta para este elemeto y esta deberá ser validada por Odata | J41: =IF(Tabla1[[#This Row],[Respuesta]]="","Sin respuesta","Respondido") -> Respondido
A42: 443 | B42: 26 | C42: Fleischmann S. A. | E42: ELECTRICO | F42: Se solicita indicar hasta que eje se debe considerar el suministro de los Pararrayos y el FLEJE DE ALUMINIO 25x8mm (1"x1/4") - en el ed. General | H42: Solo lo indicado como Fase 5, eje CL. | J42: =IF(Tabla1[[#This Row],[Respuesta]]="","Sin respuesta","Respondido") -> Respondido
A43: 442 | B43: 25 | C43: Fleischmann S. A. | E43: ELECTRICO | F43: Se solicita indicar hasta que eje se debe considerar el alumbrado perimetral del ed. General | H43: El alcance del Alumbrado perimetral es hasta el eje CL. | J43: =IF(Tabla1[[#This Row],[Respuesta]]="","Sin respuesta","Respondido") -> Respondido
A44: 441 | B44: 24 | C44: Fleischmann S. A. | E44: ELECTRICO | F44: Se solicita confirmar si las bases de los poste de CCTV se encuentran aterrizadas, y con el cable de tierra para aterrizar el poste. | H44: Es alcance del Proponente. | J44: =IF(Tabla1[[#This Row],[Respuesta]]="","Sin respuesta","Respondido") -> Respondido
A45: 440 | B45: 23 | C45: Fleischmann S. A. | E45: ELECTRICO | F45: Se solicita confirmar si las bases de los poste de alumbrado se encuentran aterrizadas, y con el cable de tierra para aterrizar el poste. | H45: Es alcance del Proponente. | J45: =IF(Tabla1[[#This Row],[Respuesta]]="","Sin respuesta","Respondido") -> Respondido
A46: 439 | B46: 22 | C46: Fleischmann S. A. | E46: ELECTRICO | F46: Se solicita confirmar si las cámaras Eléctricas se encuentra aterrizadas y barra con terminales. | H46: Es alcance del Proponente. | J46: =IF(Tabla1[[#This Row],[Respuesta]]="","Sin respuesta","Respondido") -> Respondido
A47: 438 | B47: 21 | C47: Fleischmann S. A. | E47: ELECTRICO | F47: Se solicita confirmar si las cámaras Eléctricas se encuentra con la ferretería para el paso de los conductores. | H47: Es alcance del Proponente. | J47: =IF(Tabla1[[#This Row],[Respuesta]]="","Sin respuesta","Respondido") -> Respondido
A48: 437 | B48: 20 | C48: Fleischmann S. A. | E48: ELECTRICO | F48: Se solicita confirmar si las Canastillo porta conductores de Electricidad serán Electro-galvanizadas, Galvanizadas en caliente o pintadas "indicar color", para las de interior como las de exterior | H48: Considerar galvanizados en caliente para exterior y electro-galvanizados para interior. | J48: =IF(Tabla1[[#This Row],[Respuesta]]="","Sin respuesta","Respondido") -> Respondido
A49: 436 | B49: 19 | C49: Fleischmann S. A. | E49: ELECTRICO | F49: Se solicita confirmar si las Bandejas porta conductores de Electricidad serán Electro-galvanizadas, Galvanizadas en caliente o pintadas "indicar color", para las de interior como las de exterior | H49: Considerar galvanizadas en caliente para exterior y electro-galvanizadas para interior. | J49: =IF(Tabla1[[#This Row],[Respuesta]]="","Sin respuesta","Respondido") -> Respondido
... A61: 424 | B61: 7 | C61: Fleischmann S. A. | E61: ELECTRICO | F61: Se solicita confirmar quien será el responsable del suministro de los banco de carga para las pruebas de comisionamineto, cuanto tiempo de arriendo se debe considerar. | H61: Es responsabilidad del Proponente. Ver alcance del RFP. | J61: =IF(Tabla1[[#This Row],[Respuesta]]="","Sin respuesta","Respondido") -> Respondido
A62: 423 | B62: 6 | C62: Fleischmann S. A. | E62: ELECTRICO | F62: Se solicita confirmar quien será el responsable del suministro y montaje de las bandejas tipo DLP que se proyectan en muebles y muros en el ed. Administrativo, de ser del GC se solicita enviar EETT o detalles técnicos para su valorización. | G62: ODA-0004-ELE-PL-051 | H62: No forman parte del alcance de este RFP. | J62: =IF(Tabla1[[#This Row],[Respuesta]]="","Sin respuesta","Respondido") -> Respondido
A63: 422 | B63: 5 | C63: Fleischmann S. A. | E63: ELECTRICO | F63: En el documento "Consolidado Consulta y respuestas FASE 5_E2_r0", ítem n°19 se consulta por la Ubicación de los Cargadores de Vehículos, pero en los planos que entregaron como respuesta no especifica la ubicación, se solicita enviar ubicación de estos cargadores. | H63: Ver respuesta 19. | J63: =IF(Tabla1[[#This Row],[Respuesta]]="","Sin respuesta","Respondido") -> Respondido
A64: 421 | B64: 4 | C64: Fleischmann S. A. | E64: ELECTRICO | F64: Se solicita envía documento "ODA-0004-ELE-LI-703" actualizado donde se proyecte el alimentador del tablero TDF-SDU-AUT-7.R. | H64: Ver Respuesta 295. | J64: =IF(Tabla1[[#This Row],[Respuesta]]="","Sin respuesta","Respondido") -> Respondido
A65: 420 | B65: 3 | C65: Fleischmann S. A. | E65: ELECTRICO | F65: Se solicita envía diagrama unilineal de la lamina "ODA-0004-ELE-PL-703" actualizado donde se proyecte el alimentador del tablero TDF-SDU-AUT-7.R. | H65: Ver Respuesta 295. | J65: =IF(Tabla1[[#This Row],[Respuesta]]="","Sin respuesta","Respondido") -> Respondido
A66: 419 | B66: 2 | C66: Fleischmann S. A. | E66: ELECTRICO | F66: Se solicita confirmar, si Odata será el responsable del suministro y montaje de estos Tableros Principales: 1.2.1 Distribución Principal T.D.F.-MSB-7.1 1.2.2 Distribución Principal T.D.F.-MSB-7.2 1.2.3 Distribución Principal T.D.F.-MSB-7.R 1.2.4 Distribución Principal T.D.F.-MSB-ADM.2 1.2.5 Tablero de distribución T.D.U.7.1-DP-UPS-7.1 1.2.6 Tablero de distribución T.D.U.7.2-DP-UPS-7.2 1.2.7 Tablero de distribución T.D.U.7.R-DP-UPS-7.R 1.2.8 Tablero de distribución T.D.U.ADM.2-DP-UPS-ADM.2 1.2.9 Tablero T.D.F.-QBM-7.1 1.2.10 Tablero T.D.F.-QBM-7.2 1.2.11 Tablero T.D.F.-QBM-7.R | H66: Si, se confirma. | J66: =IF(Tabla1[[#This Row],[Respuesta]]="","Sin respuesta","Respondido") -> Respondido
A67: 418 | B67: 1 | C67: Fleischmann S. A. | E67: ELECTRICO | F67: Según el documento "RFP INSTALCIONES EX05_REV2" los equipos suministrados por Odata Son: o RMU (Ring Main Unit), o Transformador XFMR, o Grupos Generadores, o Sistema UPS, Bancos de Baterías y Tableros de Paralelismo, o Conmutador STS (Static Transfer Switch), o Unidad PDU (Power Distribution Units), o LV Switchgear. o Equipos RPP Pero en el Anexo IX "ANEXO IX_Listado de Equipos Suministro Odata_rev2", no incluyeron: oBancos de Baterías y Tableros de Paralelismo, o LV Switchgear. o Equipos RPP Se solicita confirmar de forma clara cuales son los equipos que se suministrarán. | G67: ANEXO IX_Listado de Equipos Suministro Odata_rev2 RFP INSTALCIONES EX05_REV2 | H67: Prevalece listado indicado en el RFP. | J67: =IF(Tabla1[[#This Row],[Respuesta]]="","Sin respuesta","Respondido") -> Respondido
A68: 417 | C68: CS Energy | E68: GENERAL/ADM | F68: En la Gestión de Interferencias e ISSUES es posible utilizar las nuevas herramientas que el ACC nos ofrece como BIM COLLABORATE PRO | H68: Es posible pero se acordara con posterioridad al cierre de la licitación. | J68: =IF(Tabla1[[#This Row],[Respuesta]]="","Sin respuesta","Respondido") -> Respondido
A69: 416 | C69: CS Energy | E69: GENERAL/ADM | F69: El entorno Común de datos indicado en el PEB de proyecto es BIM 360. Informar que éste año BIM 360 dejará de funcionar y tener soporte Autodesk. Confirmar si es posible migrar todo a Autodesk Construcción Cloud: ACC Docs, Model Coordination y ACC BUILD | H69: Es posible pero se acordara con posterioridad al cierre de la licitación. | J69: =IF(Tabla1[[#This Row],[Respuesta]]="","Sin respuesta","Respondido") -> Respondido
A70: 415 | C70: CS Energy | E70: GENERAL/ADM | F70: La versión indicada en el PEB Plan de ejecución BIM de proyecto es revit 2022. confirmar si se puede actualizar todo a Revit 2025 o 2026 | H70: No se puede ajustar | J70: =IF(Tabla1[[#This Row],[Respuesta]]="","Sin respuesta","Respondido") -> Respondido
A71: 414 | C71: CS Energy | E71: GENERAL/ADM | F71: Favor de entregar el Plan de Ejecución BIM para Obra? | H71: N/A | J71: =IF(Tabla1[[#This Row],[Respuesta]]="","Sin respuesta","Respondido") -> Respondido
A72: 413 | C72: CS Energy | E72: GENERAL/ADM | F72: Revisado el estado de coordinación de modelos se observan mejoras y oportunidades para minimizar o anular el impacto de la situación a actual de modelos. Para ello es necesario AJUSTAR TRAZADOS es por ello que necesitamos aclarar lo siguiente: | H72: Es responsabilidad del Proponente, ver respuestas 23, 140, 236 y 241 . Ver numerales 4.3.8, 5.4 y 5.5 del RFP | J72: =IF(Tabla1[[#This Row],[Respuesta]]="","Sin respuesta","Respondido") -> Respondido
A73: 412 | C73: CS Energy | E73: GENERAL/ADM | F73: Favor entregar Plano viales para posicionamiento de grúas y camiones o modelo topográfico y de pavimentación | H73: Utilizar planos de arquitectura adjuntos, las estrategias de grúas es exclusiva responsabilidad del proponente. | J73: =IF(Tabla1[[#This Row],[Respuesta]]="","Sin respuesta","Respondido") -> Respondido
A74: 411 | C74: CS Energy | E74: GENERAL/ADM | F74: Favor entregar modelo BIM Asbuilt de arquitectura y estructuras detalladas realmente construidas | H74: No se requiere y no forma parte de la licitación | J74: =IF(Tabla1[[#This Row],[Respuesta]]="","Sin respuesta","Respondido") -> Respondido
A75: 410 | C75: CS Energy | E75: GENERAL/ADM | F75: Favor entregar mecánica de suelo | H75: No se requiere y no forma parte de la licitación | J75: =IF(Tabla1[[#This Row],[Respuesta]]="","Sin respuesta","Respondido") -> Respondido
A76: 409 | C76: CS Energy | E76: GENERAL/ADM | F76: Favor entregar modelo BIM y estudio topográfico | H76: Se entrega Modelo BIM, Estudio Topografico No se requiere y no forman parte de la licitación. | J76: =IF(Tabla1[[#This Row],[Respuesta]]="","Sin respuesta","Respondido") -> Respondido
A77: 408 | C77: CS Energy | E77: GENERAL/ADM | F77: Favor entregar Estudio de inundación y cota mínima instalaciones | H77: No se requieren y no forman parte de la licitación. | J77: =IF(Tabla1[[#This Row],[Respuesta]]="","Sin respuesta","Respondido") -> Respondido
A78: 407 | C78: CS Energy | E78: HVAC | F78: Se solicita entregar tamaño de estanque de inercia/termo acumulación de Chillers. Proyecto indica 2m3 siendo un volumen insuficiente para termo acumulación. | H78: Ver Respuesta 321. | J78: =IF(Tabla1[[#This Row],[Respuesta]]="","Sin respuesta","Respondido") -> Respondido
A79: 406 | C79: CS Energy | E79: OOCC | F79: Confirmar si el piso Técnico debe considerar palmetas de alto flujo de aire, si es así, mencionar % del flujo de las palmetas. | H79: Ver Respuesta 345. | J79: =IF(Tabla1[[#This Row],[Respuesta]]="","Sin respuesta","Respondido") -> Respondido
... A96: 389 | C96: CS Energy | E96: GENERAL/ADM | F96: Confirmar que los proveedores de los equipos suministraran bases y anclajes antisísmicos | H96: Remítase al alcance del RFP para cada equipo indicado. | J96: =IF(Tabla1[[#This Row],[Respuesta]]="","Sin respuesta","Respondido") -> Respondido
A97: 388 | B97: 21 | C97: Propamat | E97: DETECCION | F97: ¿Se debe considerar sistema de detección de incendio para los Colos 8, 9, salas eléctricas 8.1, 8.2, 9.1, 9.2, corredores técnicos 8.1, 8.2, 9.1 y 9.2? | H97: Remítase al alcance del RFP para cada equipo indicado. | J97: =IF(Tabla1[[#This Row],[Respuesta]]="","Sin respuesta","Respondido") -> Respondido
A98: 387 | B98: 20 | C98: Propamat | E98: TELECOM | F98: ¿Se debe considerar el suministro e instalación de los racks de comunicaciones y PDU Verticales? | H98: Se deben considerar en la Oferta | J98: =IF(Tabla1[[#This Row],[Respuesta]]="","Sin respuesta","Respondido") -> Respondido
A99: 386 | B99: 19 | C99: Propamat | E99: TELECOM | F99: ¿Se debe considerar el suministro, instalación y configuración del equipamiento activo (Router, Firewall, Switch, Access Point? | H99: Odata suministrará y configurará. El Proponente deberá apoyar con la instalación y el aporte de todos los misceláneos para su puesta en servicio | J99: =IF(Tabla1[[#This Row],[Respuesta]]="","Sin respuesta","Respondido") -> Respondido
A100: 385 | B100: 18 | C100: Propamat | E100: SEGURIDAD | F100: ¿Se deben suministrar los servidores de grabación de 400TB para la grabación de video? | H100: Odata suministrará los servidores correspondiente, en donde el Proponente debe aportar todos los misceláneos y apoyar con su instalación | J100: =IF(Tabla1[[#This Row],[Respuesta]]="","Sin respuesta","Respondido") -> Respondido
A101: 384 | B101: 17 | C101: Propamat | E101: SEGURIDAD | F101: ¿Se puede utilizar módulos de entradas y salidas compatibles con la plataforma existente SecurityXpert para los tableros TIM? | H101: Si, se puede considerar. | J101: =IF(Tabla1[[#This Row],[Respuesta]]="","Sin respuesta","Respondido") -> Respondido
A102: 383 | B102: 16 | C102: Propamat | E102: SEGURIDAD | F102: ¿Se debe considerar enlaces redundantes para los tableros convertidores de medios de las cámaras exteriores? | H102: Ofertar lo indicado en proyecto | J102: =IF(Tabla1[[#This Row],[Respuesta]]="","Sin respuesta","Respondido") -> Respondido
A103: 382 | B103: 15 | C103: Propamat | E103: BMS | F103: ¿El tablero QA-AGREG-002 debe considerarse todo el equipamiento que salen en el documento ODA-0004-AUT-PL-0001? | H103: Solo Colo 7, sin embargo el tablero deberá estar adecuado para la integración de los dispositivos futuros | J103: =IF(Tabla1[[#This Row],[Respuesta]]="","Sin respuesta","Respondido") -> Respondido
A104: 381 | B104: 14 | C104: Propamat | E104: BMS | F104: ¿Se debe considerar el suministro, instalación y configuración del sistema Tahuya (controladores y tablero)? | H104: Se deben considerar en la Oferta | J104: =IF(Tabla1[[#This Row],[Respuesta]]="","Sin respuesta","Respondido") -> Respondido
A105: 380 | B105: 13 | C105: Propamat | E105: BMS | F105: Para video wall de la sala NOC ¿Se debe considerar Video Wall de 24 pantallas de la marca BARCO? | H105: Debe ser de 24 pantallas y la marca debe cumplir las EETT del proyecto | J105: =IF(Tabla1[[#This Row],[Respuesta]]="","Sin respuesta","Respondido") -> Respondido
A106: 379 | B106: 12 | C106: Propamat | E106: BMS | F106: ¿Se debe considerar el cableado de los sensores de temperatura y humedad, sensores de temperatura ambiental, de presión diferencial, transmisores de temperatura, válvulas de presión y leak detectors del sistema Delta Cube? | H106: Se deben considerar en la Oferta | J106: =IF(Tabla1[[#This Row],[Respuesta]]="","Sin respuesta","Respondido") -> Respondido
A107: 378 | B107: 11 | C107: Propamat | E107: BMS | F107: ¿Se debe considerar mejoras a los servidores del Scada Ignition? o ¿Se debe considerar nuevos servidores para el Scada Ignition? | H107: Odata suministrará los servidores correspondiente, en donde el Proponente debe aportar todos los misceláneos y apoyar con su instalación | J107: =IF(Tabla1[[#This Row],[Respuesta]]="","Sin respuesta","Respondido") -> Respondido
A108: 377 | B108: 10 | C108: Propamat | E108: ELECTRICO | F108: Confirmar que el sistema de descargas atmosféricas (pararrayos), debe ser considerado de acuerdo al modelo de la etapa anterior (pararrayos activo), lo cual reemplazaría a lo proyectado en laminas de la presenta licitación. | H108: Si, se confirma pararrayos activo. | J108: =IF(Tabla1[[#This Row],[Respuesta]]="","Sin respuesta","Respondido") -> Respondido
... A147: 337 | B147: 85 | C147: Tecsa | E147: ELECTRICO | F147: ELECTRICO: ¿Se debe considerar energía de respaldo como mitigación en el proceso de pruebas de comisionamiento ? | H147: No se requiere. | J147: =IF(Tabla1[[#This Row],[Respuesta]]="","Sin respuesta","Respondido") -> Respondido
A148: 336 | B148: 84 | C148: Tecsa | E148: GENERAL/ADM | F148: TODAS LAS ESPECIALIDADES: ¿Existen documentos protocolizados para las actividades a desarrollar? Si es así ¿nos los pueden compartir? | G148: MONITOREO DEL DESEMPEÑO DE LA CALIDAD DE LA CONSTRUCCIÓN CONSTRUCTION QUALITY PERFORMANCE MONITORING | H148: El Proponente debe adherirse a la Plataforma Cx Alloy. No existen formatos, el proponente debe utilizar sus protocolos, presentar y completar o modificar de ser solicitado. | J148: =IF(Tabla1[[#This Row],[Respuesta]]="","Sin respuesta","Respondido") -> Respondido
A149: 335 | B149: 83 | C149: Tecsa | E149: ELECTRICO | F149: ELECTRICO: ¿Se utilizará una plataforma para el registro del proceso de comisionamiento? | H149: Para el Proyecto ST-01 se cuenta con una plataforma de gestión denominada CX Alloy, la cual integra y atiende de manera centralizada los ámbitos de Calidad, Seguridad, Puesta en Marcha y Comisionamiento. Dicha plataforma constituye un requisito establecido por ODATA en materia de aseguramiento y control de procesos, permitiendo la trazabilidad, seguimiento y validación de cada etapa crítica del proyecto. En este sentido, el Proponente debe adherirse a esta metodología de gestión, asegurando el registro y cumplimiento de los lineamientos definidos en el marco contractual. | J149: =IF(Tabla1[[#This Row],[Respuesta]]="","Sin respuesta","Respondido") -> Respondido
A150: 334 | B150: 82 | C150: Tecsa | E150: ELECTRICO | F150: ELECTRICO: ¿Se posee un plan de comisionamiento? Si es así ¿nos lo pueden compartir? | H150: Por el momento no contamos con dicho plan | J150: =IF(Tabla1[[#This Row],[Respuesta]]="","Sin respuesta","Respondido") -> Respondido
A151: 333 | B151: 81 | C151: Tecsa | E151: ELECTRICO | F151: ELECTRICO: Se solicita fleje de cobre 25x8mm para aterramiento de tableros y equipos, ¿se puede remplazar por cable de cobre desnudo 2/0? | H151: NO. Considerar solo lo indicado en proyecto | J151: =IF(Tabla1[[#This Row],[Respuesta]]="","Sin respuesta","Respondido") -> Respondido
A152: 332 | B152: 80 | C152: Tecsa | E152: ELECTRICO | F152: ELECTRICO: ¿Se requiere realizar una nueva medición del sistema de malla de tierra una vez instalados todos los equipos? | H152: NO. Considerar solo lo indicado en proyecto | J152: =IF(Tabla1[[#This Row],[Respuesta]]="","Sin respuesta","Respondido") -> Respondido
A153: 331 | B153: 79 | C153: Tecsa | E153: ELECTRICO | F153: ELECTRICO: Para la continuación del ducto de barra de las etapas futuras de los Colos 8 y 9, se recomienda instalar un tablero seccionador para así no tener que cortar el suministro eléctrico y poder realizar las futuras instalaciones sin ningún problema. | H153: No se acoge la recomendación | J153: =IF(Tabla1[[#This Row],[Respuesta]]="","Sin respuesta","Respondido") -> Respondido
A154: 330 | B154: 78 | C154: Tecsa | E154: ELECTRICO | F154: ELECTRICO: Los conductores para la alimentación de los equipos al interior de un Data Center (RIC N°11) deberán ser libres de halógeno, no propagante de la llama y autoextinguibles, en cumplimiento a lo indicado en el punto 5.5 del pliego técnico normativo RIC N°04, por lo cual se recomienda cable RZ1-K. | H154: Ofertar de acuerdo a lo especificado en el proyecto | J154: =IF(Tabla1[[#This Row],[Respuesta]]="","Sin respuesta","Respondido") -> Respondido
A155: 329 | B155: 77 | C155: Tecsa | E155: ELECTRICO | F155: ELECTRICO: ¿Se debe considerar dilatación sísmica para el recorrido de ducto barra? | H155: Dependerá de la propuesta del Vendor de ducto de barra | J155: =IF(Tabla1[[#This Row],[Respuesta]]="","Sin respuesta","Respondido") -> Respondido
A156: 328 | B156: 76 | C156: Tecsa | E156: ELECTRICO | F156: ELECTRICO: ¿El alimentador provisorio retirado en la Fase 3 se reutiliza? | H156: No se reutiliza, se entrega a Odata. | J156: =IF(Tabla1[[#This Row],[Respuesta]]="","Sin respuesta","Respondido") -> Respondido
A157: 327 | B157: 75 | C157: Tecsa | E157: ELECTRICO | F157: ELECTRICO: ¿Los conectores CamLock para el proceso de comisionamiento son provistos por el proveedor de los Grupos electrógenos o deben ser suministrados de esta licitación? | H157: Deben ser suministrados por el Proponente | J157: =IF(Tabla1[[#This Row],[Respuesta]]="","Sin respuesta","Respondido") -> Respondido
A158: 326 | B158: 74 | C158: Tecsa | E158: ELECTRICO | F158: ELECTRICO: ¿Las bajantes del sistema pararrayos se deben conectar a la malla de tierra existente o se debe realizar una malla de tierra independiente con caja de inspección y ecualizador de potencia por cada una de ellas? Si fuera la opción de la malla de tierra existente sin caja de registro, ¿existentes estos "chicotes" para conectarse a estos por termofusión? | H158: Se deberá conectar a la malla de tierra existente. Los chicotes son existentes | J158: =IF(Tabla1[[#This Row],[Respuesta]]="","Sin respuesta","Respondido") -> Respondido
A159: 325 | B159: 73 | C159: Tecsa | E159: GENERAL/ADM | F159: TODAS LAS ESPECIALIDADES: Para las tareas de responsabilidad del Proveedor, ¿cuál es el alcance como “Facilitador” del Proponente en lo que respecta a carga, descarga, traslado y posicionamiento de equipos? | H159: El Proponente deberá proporcionar los accesos, vías de tránsito y espacios adecuados, así como ejecutar las adecuaciones necesarias que permitan de manera segura y eficiente las actividades de carga, descarga, traslado y posicionamiento de equipos. | J159: =IF(Tabla1[[#This Row],[Respuesta]]="","Sin respuesta","Respondido") -> Respondido
A160: 324 | B160: 72 | C160: Tecsa | E160: GENERAL/ADM | F160: TODAS LAS ESPECIALIDADES: ¿Es necesario contratar un seguro para los equipos provistos por los proveedores? | H160: No es requisito. Ver respuesta 323. | J160: =IF(Tabla1[[#This Row],[Respuesta]]="","Sin respuesta","Respondido") -> Respondido
... A230: 253 | B230: 1 | C230: Tecsa | E230: EHS | F230: En el itemizado ítem 11.3 se solicita presupuestar línea de vida vertical puntual sobre cielo falso. Favor enviar detalle y desarrollo de dicha línea de vida para poder cotizarla y cuantificarla, ya que dentro de los antecedentes que tenemos no se logra identificar. | H230: Ver plano ODA-0004-ARQ-PL-046 y EETT 6.1.2 Líneas de vida. El Proponente deberá presentar un diseño que se ajuste íntegramente a la normativa vigente y a las disposiciones técnicas aplicable. | J230: =IF(Tabla1[[#This Row],[Respuesta]]="","Sin respuesta","Respondido") -> Respondido
A231: 252 | B231: 143 | C231: Global Data | D231: Técnicas | E231: ELECTRICO | F231: En relación a listado de tableros eléctricos de baja tensión. Indicar en qué planos se encuentran los diagramas unilineales faltantes o, de ser posible, enviarlos. Tableros pendientes "T.D.A.F-FL-ADM2-01", "T.D.A.F-FL-ADM2-02", "T.D.A.F-HVAC-ADM2-01", "T.D.A.F-HVAC-ADM2-01", "T.D.A.F-HVAC-ADM2-02", "Tablero T.D.F.-SDU-AUT-7.R", "T.D.F-EMERG-ADM2.01", "T.D.F-EMERG-ADM2.02", "T.D.A.F-BBAS-ADM.2", "T.D.F-NOC-ADM.2" | G231: ODA-0004-ELE-PL-060 ODA-0004-ELE-PL-061 ODA-0004-ELE-PL-062 ODA-0004-ELE-PL-063 ODA-0004-ELE-PL-067 ODA-0004-ELE-PL-068 ODA-0004-ELE-PL-066 | H231: Se envían planos ODA-0004-ELE-PL-060, ODA-0004-ELE-PL-061, ODA-0004-ELE-PL-062, ODA-0004-ELE-PL-063, ODA-0004-ELE-PL-067, ODA-0004-ELE-PL-068 y ODA-0004-ELE-PL-066. | J231: =IF(Tabla1[[#This Row],[Respuesta]]="","Sin respuesta","Respondido") -> Respondido
A232: 251 | B232: 142 | C232: Global Data | D232: Técnicas | E232: TELECOM | F232: ¿Se exige entregar manuales O&M y capacitación antes de recepción provisoria? | H232: Si, según lo indicado en este RFP y las clausulas del Contrato. | J232: =IF(Tabla1[[#This Row],[Respuesta]]="","Sin respuesta","Respondido") -> Respondido
A233: 250 | B233: 141 | C233: Global Data | D233: Técnicas | E233: TELECOM | F233: ¿El Mandante proveerá acceso a as-built previos para planificar rutas? | H233: Ver Respuesta 237. | J233: =IF(Tabla1[[#This Row],[Respuesta]]="","Sin respuesta","Respondido") -> Respondido
A234: 249 | B234: 140 | C234: Global Data | D234: Técnicas | E234: TELECOM | F234: ¿Cuál será la secuencia de entregas: Colo 7 primero, luego 8 y 9? | H234: El alcance de este RFP para los sistemas de Telecomunicaciones corresponde Solo a la Fase 5. | J234: =IF(Tabla1[[#This Row],[Respuesta]]="","Sin respuesta","Respondido") -> Respondido
A235: 248 | B235: 139 | C235: Global Data | D235: Técnicas | E235: TELECOM | F235: ¿Se ha considerado commissioning independiente de telecom antes del IST? | H235: Ver Respuesta 237. | J235: =IF(Tabla1[[#This Row],[Respuesta]]="","Sin respuesta","Respondido") -> Respondido
...
